tests/__init__.py
tests/test_CTS2IPA.py
tests/test_CTS2UAS.py
tests/test_CTS2UZBEK.py
tests/test_CTS2XJUS.py
tests/test_UAS2CTS.py
tests/test_UAS2UCS.py
tests/test_UAS2ULS.py
tests/test_UCS2UAS.py
tests/test_ULS2UAS.py
tests/test_UZBEK2CTS.py
tests/test_XJUS2CTS.py
tests/test_XJUS2UAS.py
umsc/__init__.py
umsc/umsc.py
umsc-0.4.0.dist-info/LICENSE
umsc-0.4.0.dist-info/METADATA
umsc-0.4.0.dist-info/WHEEL
umsc-0.4.0.dist-info/top_level.txt
umsc-0.4.0.dist-info/RECORD
