Metadata-Version: 2.1
Name: umsc
Version: 0.4.0
Summary: Script Converter for Uyghur Language
Home-page: https://github.com/neouyghur/ScriptConverter4Uyghur
Author: Osman Tursun
Author-email: osmanjan.t@gmail.com
Maintainer: Osman Tursun
Maintainer-email: mpcabd@gmail.com
Keywords: uyghur script converter arabic latin cyrillic IPA ئۇيغۇر
Classifier: Programming Language :: Python :: 3
Classifier: License :: OSI Approved :: Apache Software License
Classifier: Operating System :: OS Independent
Requires-Python: >=3.0
License-File: LICENSE
Requires-Dist: regex
